freshchat/client/__init__.py
freshchat/client/client.py
freshchat/client/configuration.py
freshchat/client/exceptions.py
freshchat/client/responses.py
freshchat/models/__init__.py
freshchat/models/events.py
freshchat/webhook/__init__.py
freshchat/webhook/security.py
freshchat-0.5.0.dist-info/LICENSE
freshchat-0.5.0.dist-info/WHEEL
freshchat-0.5.0.dist-info/METADATA
freshchat-0.5.0.dist-info/RECORD
