Metadata-Version: 2.1
Name: freshchat
Version: 0.5.0
Summary: A library provide a http client for Freshchat API
Home-page: https://github.com/twyla-ai/python-freshchat
License: MIT
Author: Twyla Engineering
Author-email: software@twyla.ai
Requires-Python: >=3.6,<4.0
Classifier: License :: OSI Approved :: MIT License
Classifier: Programming Language :: Python :: 3
Classifier: Programming Language :: Python :: 3.6
Classifier: Programming Language :: Python :: 3.7
Classifier: Programming Language :: Python :: 3.8
Requires-Dist: aiohttp (>=3.6,<4.0)
Requires-Dist: cafeteria (>=0.19,<0.20)
Requires-Dist: dataclasses (>=0.6,<0.8); python_version >= "3.6" and python_version < "3.7"
Requires-Dist: pycrypto (>=2.6,<3.0)
Project-URL: Repository, https://github.com/twyla-ai/python-freshchat
